persian_names/__init__.py
persian_names/p.py
persian_names/persian_names.py
persian_names/data/female.txt
persian_names/data/female_en.txt
persian_names/data/female_fa.txt
persian_names/data/male.txt
persian_names/data/male_en.txt
persian_names/data/male_fa.txt
persian_names/data/region_en.txt
persian_names/data/region_fa.txt
persian_names-1.5.1.data/data/female_en.txt
persian_names-1.5.1.data/data/female_fa.txt
persian_names-1.5.1.data/data/male_en.txt
persian_names-1.5.1.data/data/male_fa.txt
persian_names-1.5.1.data/data/region_en.txt
persian_names-1.5.1.data/data/region_fa.txt
persian_names-1.5.1.dist-info/LICENSE
persian_names-1.5.1.dist-info/METADATA
persian_names-1.5.1.dist-info/WHEEL
persian_names-1.5.1.dist-info/top_level.txt
persian_names-1.5.1.dist-info/RECORD
