Metadata-Version: 2.1
Name: persian-names
Version: 1.5.1
Summary: A Python package for generating random Persian (Farsi) names.
Home-page: https://github.com/armanyazdi/persian-names
Author: Arman Yazdi
License: MIT
Project-URL: Source, https://github.com/armanyazdi/persian-names
Project-URL: Documentation, https://pypi.org/project/persian-names
Keywords: persian names,farsi names,iranian names,name generator
Platform: UNKNOWN
Classifier: License :: OSI Approved :: MIT License
Classifier: Natural Language :: Persian
Classifier: Natural Language :: English
Classifier: Programming Language :: Python
Classifier: Programming Language :: Python :: 3
Classifier: Programming Language :: Python :: 3.4
Classifier: Programming Language :: Python :: 3.5
Classifier: Programming Language :: Python :: 3.6
Classifier: Programming Language :: Python :: 3.7
Classifier: Programming Language :: Python :: 3.8
Classifier: Programming Language :: Python :: 3.9
Classifier: Programming Language :: Python :: 3.10
Classifier: Programming Language :: Python :: 3.11
Classifier: Programming Language :: Python :: 3.12
Classifier: Topic :: Software Development :: Libraries
Classifier: Topic :: Software Development :: Libraries :: Python Modules
Classifier: Topic :: Software Development :: Localization
License-File: LICENSE
